generate_elan/__init__.py
generate_elan/__main__.py
generate_elan-1.1.0.dist-info/METADATA
generate_elan-1.1.0.dist-info/WHEEL
generate_elan-1.1.0.dist-info/top_level.txt
generate_elan-1.1.0.dist-info/RECORD
