Metadata-Version: 2.1
Name: generate-elan
Version: 1.1.0
Summary: Automatic ELAN generation package.
Home-page: UNKNOWN
Author: Md. Shahad Mahmud Chowdhury
Author-email: shahad9381@gmail.com
License: UNKNOWN
Keywords: STT,ASR,TTS,ELAN,annotation
Platform: UNKNOWN
Classifier: Programming Language :: Python :: 3
Requires-Python: >=3.6
Requires-Dist: pympi-ling
Requires-Dist: tqdm
